beancount_swile/__init__.py
beancount_swile-0.1.3.dist-info/WHEEL
beancount_swile-0.1.3.dist-info/METADATA
beancount_swile-0.1.3.dist-info/RECORD
