Metadata-Version: 2.1
Name: beancount-swile
Version: 0.1.3
Summary: Beancount Importer for Swile transactions
Home-page: https://github.com/Eazhi/beancount-swile
License: MIT
Keywords: banking,beancount,cli-accounting,finance
Author: Paul Khuat-Duy
Author-email: paul@khuat-duy.org
Requires-Python: >=3.8,<4.0
Classifier: Environment :: Plugins
Classifier: Intended Audience :: Financial and Insurance Industry
Classifier: License :: OSI Approved :: MIT License
Classifier: Programming Language :: Python :: 3
Classifier: Programming Language :: Python :: 3 :: Only
Classifier: Programming Language :: Python :: 3.10
Classifier: Programming Language :: Python :: 3.8
Classifier: Programming Language :: Python :: 3.9
Classifier: Topic :: Office/Business :: Financial
Classifier: Topic :: Office/Business :: Financial :: Accounting
Requires-Dist: beancount (>=2.3.5,<3.0.0)
Requires-Dist: requests (>=2.28.1,<3.0.0)
Requires-Dist: typer (>=0.6.1,<0.7.0)
Project-URL: Repository, https://github.com/Eazhi/beancount-swile
